easiofy_data_anonymization/__init__.py
easiofy_data_anonymization/api.py
easiofy_data_anonymization/encrypted_creds.txt
easiofy_data_anonymization-2.6.dist-info/METADATA
easiofy_data_anonymization-2.6.dist-info/WHEEL
easiofy_data_anonymization-2.6.dist-info/entry_points.txt
easiofy_data_anonymization-2.6.dist-info/top_level.txt
easiofy_data_anonymization-2.6.dist-info/RECORD
