Metadata-Version: 2.1
Name: easiofy-data-anonymization
Version: 2.6
Summary: A FastAPI application for DICOM data anonymization.
Author: Easiofy Pvt Ltd
Author-email: info@easiofy.com
Classifier: Programming Language :: Python :: 3
Classifier: License :: OSI Approved :: MIT License
Classifier: Operating System :: OS Independent
Requires-Python: >=3.6
Requires-Dist: fastapi
Requires-Dist: uvicorn
Requires-Dist: aiohttp
Requires-Dist: firebase-admin
Requires-Dist: pydicom
Requires-Dist: python-multipart
Requires-Dist: werkzeug
Requires-Dist: python-dotenv
